{"Caspian": {"pop": "644700279", "controlled_by": "us"}, "Neapolis": {"pop": "248486110", "controlled_by": "bm"}, "Seaglory": {"pop": "402384627", "controlled_by": "gb"}, "Chalkos": {"pop": "305503668", "controlled_by": "es"}, "Goroum": {"pop": "649973513", "controlled_by": "us"}, "Newland": {"pop": "127238797", "controlled_by": "bm"}, "Gasp": {"pop": "312615004", "controlled_by": "es"}, "Regis": {"pop": "233850149", "controlled_by": "kn"}, "Tzogos": {"pop": "233955228", "controlled_by": "kn"}, "Akrotiri": {"pop": "226580505", "controlled_by": "kn"}, "Baramas": {"pop": "559476822", "controlled_by": "gd"}, "Pania": {"pop": "236369904", "controlled_by": "kn"}, "Hannes": {"pop": "328010542", "controlled_by": "es"}, "Psaral": {"pop": "208579649", "controlled_by": "kn"}, "Thorakas": {"pop": "615637718", "controlled_by": "tk"}, "St. Martins": {"pop": "242049692", "controlled_by": "kn"}, "Tortuga": {"pop": "249292274", "controlled_by": "kn"}, "Vaasburg": {"pop": "322072053", "controlled_by": "es"}, "Aiora": {"pop": "625803239", "controlled_by": "tk"}, "Kanoni": {"pop": "124748884", "controlled_by": "bm"}, "Prote": {"pop": "324018709", "controlled_by": "es"}}